[{"date":"2026-01-01","gross_revenue":60991.0,"discount_amount":4801.5,"net_revenue":56189.5,"orders":209,"diners":669,"spend_per_guest":83.990284,"spend_per_order":268.849282,"seating_rate":3.8448,"table_open_rate":5.225,"table_turnover_rate":4.225,"tables":209},{"date":"2026-01-02","gross_revenue":40614.0,"discount_amount":4196.9,"net_revenue":36417.1,"orders":131,"diners":432,"spend_per_guest":84.298843,"spend_per_order":277.99313,"seating_rate":2.4828,"table_open_rate":3.275,"table_turnover_rate":2.275,"tables":131},{"date":"2026-01-03","gross_revenue":24997.0,"discount_amount":2457.75,"net_revenue":22539.25,"orders":86,"diners":250,"spend_per_guest":90.157,"spend_per_order":262.084302,"seating_rate":1.4368,"table_open_rate":2.15,"table_turnover_rate":1.15,"tables":86},{"date":"2026-01-04","gross_revenue":14654.0,"discount_amount":1559.0,"net_revenue":13095.0,"orders":53,"diners":139,"spend_per_guest":94.208633,"spend_per_order":247.075472,"seating_rate":0.7989,"table_open_rate":1.325,"table_turnover_rate":0.325,"tables":53},{"date":"2026-01-05","gross_revenue":8601.0,"discount_amount":1017.2,"net_revenue":7583.8,"orders":31,"diners":85,"spend_per_guest":89.221176,"spend_per_order":244.63871,"seating_rate":0.4885,"table_open_rate":0.775,"table_turnover_rate":0.0,"tables":31},{"date":"2026-01-06","gross_revenue":14745.0,"discount_amount":1400.0,"net_revenue":13345.0,"orders":50,"diners":146,"spend_per_guest":91.40411,"spend_per_order":266.9,"seating_rate":0.8391,"table_open_rate":1.25,"table_turnover_rate":0.25,"tables":50},{"date":"2026-01-07","gross_revenue":12296.0,"discount_amount":1468.5,"net_revenue":10827.5,"orders":42,"diners":118,"spend_per_guest":91.758475,"spend_per_order":257.797619,"seating_rate":0.6782,"table_open_rate":1.05,"table_turnover_rate":0.05,"tables":42},{"date":"2026-01-08","gross_revenue":8149.0,"discount_amount":942.4,"net_revenue":7206.6,"orders":27,"diners":79,"spend_per_guest":91.222785,"spend_per_order":266.911111,"seating_rate":0.454,"table_open_rate":0.675,"table_turnover_rate":0.0,"tables":27},{"date":"2026-01-09","gross_revenue":15915.0,"discount_amount":2352.9,"net_revenue":13562.1,"orders":52,"diners":153,"spend_per_guest":88.641176,"spend_per_order":260.809615,"seating_rate":0.8793,"table_open_rate":1.3,"table_turnover_rate":0.3,"tables":52},{"date":"2026-01-10","gross_revenue":22450.0,"discount_amount":3450.1,"net_revenue":18999.9,"orders":78,"diners":246,"spend_per_guest":77.235366,"spend_per_order":243.588462,"seating_rate":1.4138,"table_open_rate":1.95,"table_turnover_rate":0.95,"tables":78},{"date":"2026-01-11","gross_revenue":21732.0,"discount_amount":2666.1,"net_revenue":19065.9,"orders":76,"diners":217,"spend_per_guest":87.86129,"spend_per_order":250.867105,"seating_rate":1.2471,"table_open_rate":1.9,"table_turnover_rate":0.9,"tables":76},{"date":"2026-01-12","gross_revenue":12505.0,"discount_amount":1785.6,"net_revenue":10719.4,"orders":45,"diners":116,"spend_per_guest":92.408621,"spend_per_order":238.208889,"seating_rate":0.6667,"table_open_rate":1.125,"table_turnover_rate":0.125,"tables":45},{"date":"2026-01-13","gross_revenue":10489.0,"discount_amount":736.4,"net_revenue":9752.6,"orders":36,"diners":101,"spend_per_guest":96.560396,"spend_per_order":270.905556,"seating_rate":0.5805,"table_open_rate":0.9,"table_turnover_rate":0.0,"tables":36},{"date":"2026-01-14","gross_revenue":5373.0,"discount_amount":241.5,"net_revenue":5131.5,"orders":24,"diners":56,"spend_per_guest":91.633929,"spend_per_order":213.8125,"seating_rate":0.3218,"table_open_rate":0.6,"table_turnover_rate":0.0,"tables":24},{"date":"2026-01-15","gross_revenue":11220.0,"discount_amount":1051.7,"net_revenue":10168.3,"orders":41,"diners":116,"spend_per_guest":87.657759,"spend_per_order":248.007317,"seating_rate":0.6667,"table_open_rate":1.025,"table_turnover_rate":0.025,"tables":41},{"date":"2026-01-16","gross_revenue":19497.0,"discount_amount":2047.7,"net_revenue":17449.3,"orders":66,"diners":200,"spend_per_guest":87.2465,"spend_per_order":264.383333,"seating_rate":1.1494,"table_open_rate":1.65,"table_turnover_rate":0.65,"tables":66},{"date":"2026-01-17","gross_revenue":21737.0,"discount_amount":2042.6,"net_revenue":19694.4,"orders":76,"diners":221,"spend_per_guest":89.114932,"spend_per_order":259.136842,"seating_rate":1.2701,"table_open_rate":1.9,"table_turnover_rate":0.9,"tables":76},{"date":"2026-01-18","gross_revenue":26454.0,"discount_amount":2695.9,"net_revenue":23758.1,"orders":83,"diners":240,"spend_per_guest":98.992083,"spend_per_order":286.242169,"seating_rate":1.3793,"table_open_rate":2.075,"table_turnover_rate":1.075,"tables":83},{"date":"2026-01-19","gross_revenue":16832.0,"discount_amount":1827.8,"net_revenue":15004.2,"orders":56,"diners":152,"spend_per_guest":98.711842,"spend_per_order":267.932143,"seating_rate":0.8736,"table_open_rate":1.4,"table_turnover_rate":0.4,"tables":56},{"date":"2026-01-20","gross_revenue":20476.0,"discount_amount":1163.2,"net_revenue":19312.8,"orders":73,"diners":229,"spend_per_guest":84.335371,"spend_per_order":264.558904,"seating_rate":1.3161,"table_open_rate":1.825,"table_turnover_rate":0.825,"tables":73},{"date":"2026-01-21","gross_revenue":21153.0,"discount_amount":1265.0,"net_revenue":19888.0,"orders":71,"diners":222,"spend_per_guest":89.585586,"spend_per_order":280.112676,"seating_rate":1.2759,"table_open_rate":1.775,"table_turnover_rate":0.775,"tables":71},{"date":"2026-01-22","gross_revenue":12420.0,"discount_amount":574.4,"net_revenue":11845.6,"orders":45,"diners":130,"spend_per_guest":91.12,"spend_per_order":263.235556,"seating_rate":0.7471,"table_open_rate":1.125,"table_turnover_rate":0.125,"tables":45},{"date":"2026-01-23","gross_revenue":26374.0,"discount_amount":2507.5,"net_revenue":23866.5,"orders":93,"diners":276,"spend_per_guest":86.472826,"spend_per_order":256.629032,"seating_rate":1.5862,"table_open_rate":2.325,"table_turnover_rate":1.325,"tables":93},{"date":"2026-01-24","gross_revenue":23401.0,"discount_amount":2904.0,"net_revenue":20497.0,"orders":82,"diners":244,"spend_per_guest":84.004098,"spend_per_order":249.963415,"seating_rate":1.4023,"table_open_rate":2.05,"table_turnover_rate":1.05,"tables":82},{"date":"2026-01-25","gross_revenue":22247.0,"discount_amount":1214.6,"net_revenue":21032.4,"orders":81,"diners":234,"spend_per_guest":89.882051,"spend_per_order":259.659259,"seating_rate":1.3448,"table_open_rate":2.025,"table_turnover_rate":1.025,"tables":81},{"date":"2026-01-26","gross_revenue":9170.0,"discount_amount":1075.7,"net_revenue":8094.3,"orders":34,"diners":97,"spend_per_guest":83.446392,"spend_per_order":238.067647,"seating_rate":0.5575,"table_open_rate":0.85,"table_turnover_rate":0.0,"tables":34},{"date":"2026-01-27","gross_revenue":14495.0,"discount_amount":1510.0,"net_revenue":12985.0,"orders":45,"diners":140,"spend_per_guest":92.75,"spend_per_order":288.555556,"seating_rate":0.8046,"table_open_rate":1.125,"table_turnover_rate":0.125,"tables":45},{"date":"2026-01-28","gross_revenue":13746.0,"discount_amount":548.0,"net_revenue":13198.0,"orders":44,"diners":147,"spend_per_guest":89.782313,"spend_per_order":299.954545,"seating_rate":0.8448,"table_open_rate":1.1,"table_turnover_rate":0.1,"tables":44},{"date":"2026-01-29","gross_revenue":14818.0,"discount_amount":642.5,"net_revenue":14175.5,"orders":47,"diners":150,"spend_per_guest":94.503333,"spend_per_order":301.606383,"seating_rate":0.8621,"table_open_rate":1.175,"table_turnover_rate":0.175,"tables":47},{"date":"2026-01-30","gross_revenue":25729.0,"discount_amount":2433.0,"net_revenue":23296.0,"orders":78,"diners":266,"spend_per_guest":87.578947,"spend_per_order":298.666667,"seating_rate":1.5287,"table_open_rate":1.95,"table_turnover_rate":0.95,"tables":78},{"date":"2026-01-31","gross_revenue":23535.0,"discount_amount":1483.0,"net_revenue":22052.0,"orders":84,"diners":259,"spend_per_guest":85.142857,"spend_per_order":262.52381,"seating_rate":1.4885,"table_open_rate":2.1,"table_turnover_rate":1.1,"tables":84},{"date":"2026-02-01","gross_revenue":16349.0,"discount_amount":735.0,"net_revenue":15614.0,"orders":62,"diners":179,"spend_per_guest":87.22905,"spend_per_order":251.83871,"seating_rate":1.0287,"table_open_rate":1.55,"table_turnover_rate":0.55,"tables":62},{"date":"2026-02-02","gross_revenue":12592.0,"discount_amount":415.0,"net_revenue":12177.0,"orders":40,"diners":128,"spend_per_guest":95.132812,"spend_per_order":304.425,"seating_rate":0.7356,"table_open_rate":1.0,"table_turnover_rate":0.0,"tables":40},{"date":"2026-02-03","gross_revenue":13566.0,"discount_amount":544.6,"net_revenue":13021.4,"orders":49,"diners":155,"spend_per_guest":84.009032,"spend_per_order":265.742857,"seating_rate":0.8908,"table_open_rate":1.225,"table_turnover_rate":0.225,"tables":49},{"date":"2026-02-04","gross_revenue":12792.0,"discount_amount":702.0,"net_revenue":12090.0,"orders":46,"diners":129,"spend_per_guest":93.72093,"spend_per_order":262.826087,"seating_rate":0.7414,"table_open_rate":1.15,"table_turnover_rate":0.15,"tables":46},{"date":"2026-02-05","gross_revenue":11703.0,"discount_amount":1046.4,"net_revenue":10656.6,"orders":42,"diners":132,"spend_per_guest":80.731818,"spend_per_order":253.728571,"seating_rate":0.7586,"table_open_rate":1.05,"table_turnover_rate":0.05,"tables":42},{"date":"2026-02-06","gross_revenue":15840.0,"discount_amount":1146.7,"net_revenue":14693.3,"orders":56,"diners":164,"spend_per_guest":89.593293,"spend_per_order":262.380357,"seating_rate":0.9425,"table_open_rate":1.4,"table_turnover_rate":0.4,"tables":56},{"date":"2026-02-07","gross_revenue":18815.0,"discount_amount":1864.9,"net_revenue":16950.1,"orders":66,"diners":200,"spend_per_guest":84.7505,"spend_per_order":256.819697,"seating_rate":1.1494,"table_open_rate":1.65,"table_turnover_rate":0.65,"tables":66},{"date":"2026-02-08","gross_revenue":26501.0,"discount_amount":1853.9,"net_revenue":24647.1,"orders":91,"diners":288,"spend_per_guest":85.580208,"spend_per_order":270.847253,"seating_rate":1.6552,"table_open_rate":2.275,"table_turnover_rate":1.275,"tables":91},{"date":"2026-02-09","gross_revenue":22817.0,"discount_amount":2291.5,"net_revenue":20525.5,"orders":72,"diners":234,"spend_per_guest":87.715812,"spend_per_order":285.076389,"seating_rate":1.3448,"table_open_rate":1.8,"table_turnover_rate":0.8,"tables":72},{"date":"2026-02-10","gross_revenue":18628.0,"discount_amount":1435.4,"net_revenue":17192.6,"orders":67,"diners":201,"spend_per_guest":85.535323,"spend_per_order":256.60597,"seating_rate":1.1552,"table_open_rate":1.675,"table_turnover_rate":0.675,"tables":67},{"date":"2026-02-11","gross_revenue":26810.0,"discount_amount":947.5,"net_revenue":25862.5,"orders":92,"diners":269,"spend_per_guest":96.143123,"spend_per_order":281.11413,"seating_rate":1.546,"table_open_rate":2.3,"table_turnover_rate":1.3,"tables":92},{"date":"2026-02-12","gross_revenue":17432.0,"discount_amount":706.5,"net_revenue":16725.5,"orders":59,"diners":171,"spend_per_guest":97.809942,"spend_per_order":283.483051,"seating_rate":0.9828,"table_open_rate":1.475,"table_turnover_rate":0.475,"tables":59},{"date":"2026-02-13","gross_revenue":22015.0,"discount_amount":2184.0,"net_revenue":19831.0,"orders":73,"diners":217,"spend_per_guest":91.387097,"spend_per_order":271.657534,"seating_rate":1.2471,"table_open_rate":1.825,"table_turnover_rate":0.825,"tables":73},{"date":"2026-02-14","gross_revenue":24965.0,"discount_amount":2703.8,"net_revenue":22261.2,"orders":86,"diners":231,"spend_per_guest":96.368831,"spend_per_order":258.851163,"seating_rate":1.3276,"table_open_rate":2.15,"table_turnover_rate":1.15,"tables":86},{"date":"2026-02-15","gross_revenue":10308.0,"discount_amount":428.7,"net_revenue":9879.3,"orders":33,"diners":113,"spend_per_guest":87.427434,"spend_per_order":299.372727,"seating_rate":0.6494,"table_open_rate":0.825,"table_turnover_rate":0.0,"tables":33},{"date":"2026-02-16","gross_revenue":1297.0,"discount_amount":0.0,"net_revenue":1297.0,"orders":6,"diners":13,"spend_per_guest":99.769231,"spend_per_order":216.166667,"seating_rate":0.0747,"table_open_rate":0.15,"table_turnover_rate":0.0,"tables":6},{"date":"2026-02-17","gross_revenue":4490.0,"discount_amount":0.0,"net_revenue":4490.0,"orders":17,"diners":52,"spend_per_guest":86.346154,"spend_per_order":264.117647,"seating_rate":0.2989,"table_open_rate":0.425,"table_turnover_rate":0.0,"tables":17},{"date":"2026-02-18","gross_revenue":5167.0,"discount_amount":19.0,"net_revenue":5148.0,"orders":24,"diners":76,"spend_per_guest":67.736842,"spend_per_order":214.5,"seating_rate":0.4368,"table_open_rate":0.6,"table_turnover_rate":0.0,"tables":24},{"date":"2026-02-19","gross_revenue":14575.0,"discount_amount":364.5,"net_revenue":14210.5,"orders":48,"diners":144,"spend_per_guest":98.684028,"spend_per_order":296.052083,"seating_rate":0.8276,"table_open_rate":1.2,"table_turnover_rate":0.2,"tables":48},{"date":"2026-02-20","gross_revenue":12766.0,"discount_amount":264.1,"net_revenue":12501.9,"orders":43,"diners":124,"spend_per_guest":100.821774,"spend_per_order":290.74186,"seating_rate":0.7126,"table_open_rate":1.075,"table_turnover_rate":0.075,"tables":43},{"date":"2026-02-21","gross_revenue":20795.0,"discount_amount":526.0,"net_revenue":20269.0,"orders":69,"diners":217,"spend_per_guest":93.40553,"spend_per_order":293.753623,"seating_rate":1.2471,"table_open_rate":1.725,"table_turnover_rate":0.725,"tables":69},{"date":"2026-02-22","gross_revenue":21075.0,"discount_amount":511.0,"net_revenue":20564.0,"orders":74,"diners":220,"spend_per_guest":93.472727,"spend_per_order":277.891892,"seating_rate":1.2644,"table_open_rate":1.85,"table_turnover_rate":0.85,"tables":74},{"date":"2026-02-23","gross_revenue":29379.0,"discount_amount":2706.9,"net_revenue":26672.1,"orders":96,"diners":302,"spend_per_guest":88.318212,"spend_per_order":277.834375,"seating_rate":1.7356,"table_open_rate":2.4,"table_turnover_rate":1.4,"tables":96},{"date":"2026-02-24","gross_revenue":20786.0,"discount_amount":700.5,"net_revenue":20085.5,"orders":80,"diners":234,"spend_per_guest":85.83547,"spend_per_order":251.06875,"seating_rate":1.3448,"table_open_rate":2.0,"table_turnover_rate":1.0,"tables":80},{"date":"2026-02-25","gross_revenue":18608.0,"discount_amount":689.5,"net_revenue":17918.5,"orders":60,"diners":219,"spend_per_guest":81.819635,"spend_per_order":298.641667,"seating_rate":1.2586,"table_open_rate":1.5,"table_turnover_rate":0.5,"tables":60},{"date":"2026-02-26","gross_revenue":20220.0,"discount_amount":1978.0,"net_revenue":18242.0,"orders":70,"diners":207,"spend_per_guest":88.125604,"spend_per_order":260.6,"seating_rate":1.1897,"table_open_rate":1.75,"table_turnover_rate":0.75,"tables":70},{"date":"2026-02-27","gross_revenue":21800.0,"discount_amount":1985.4,"net_revenue":19814.6,"orders":70,"diners":250,"spend_per_guest":79.2584,"spend_per_order":283.065714,"seating_rate":1.4368,"table_open_rate":1.75,"table_turnover_rate":0.75,"tables":70},{"date":"2026-02-28","gross_revenue":25833.0,"discount_amount":2521.3,"net_revenue":23311.7,"orders":90,"diners":269,"spend_per_guest":86.660595,"spend_per_order":259.018889,"seating_rate":1.546,"table_open_rate":2.25,"table_turnover_rate":1.25,"tables":90},{"date":"2026-03-01","gross_revenue":32541.0,"discount_amount":1543.0,"net_revenue":30998.0,"orders":121,"diners":338,"spend_per_guest":91.710059,"spend_per_order":256.181818,"seating_rate":1.9425,"table_open_rate":3.025,"table_turnover_rate":2.025,"tables":121},{"date":"2026-03-02","gross_revenue":18972.0,"discount_amount":648.0,"net_revenue":18324.0,"orders":69,"diners":206,"spend_per_guest":88.951456,"spend_per_order":265.565217,"seating_rate":1.1839,"table_open_rate":1.725,"table_turnover_rate":0.725,"tables":69},{"date":"2026-03-03","gross_revenue":27866.0,"discount_amount":734.5,"net_revenue":27131.5,"orders":92,"diners":287,"spend_per_guest":94.534843,"spend_per_order":294.907609,"seating_rate":1.6494,"table_open_rate":2.3,"table_turnover_rate":1.3,"tables":92},{"date":"2026-03-04","gross_revenue":14641.0,"discount_amount":656.78,"net_revenue":13984.22,"orders":51,"diners":165,"spend_per_guest":84.752848,"spend_per_order":274.200392,"seating_rate":0.9483,"table_open_rate":1.275,"table_turnover_rate":0.275,"tables":51},{"date":"2026-03-05","gross_revenue":10650.0,"discount_amount":486.5,"net_revenue":10163.5,"orders":39,"diners":112,"spend_per_guest":90.745536,"spend_per_order":260.602564,"seating_rate":0.6437,"table_open_rate":0.975,"table_turnover_rate":0.0,"tables":39},{"date":"2026-03-06","gross_revenue":15010.0,"discount_amount":2032.2,"net_revenue":12977.8,"orders":54,"diners":160,"spend_per_guest":81.11125,"spend_per_order":240.32963,"seating_rate":0.9195,"table_open_rate":1.35,"table_turnover_rate":0.35,"tables":54},{"date":"2026-03-07","gross_revenue":27069.0,"discount_amount":4572.2,"net_revenue":22496.8,"orders":92,"diners":289,"spend_per_guest":77.843599,"spend_per_order":244.530435,"seating_rate":1.6609,"table_open_rate":2.3,"table_turnover_rate":1.3,"tables":92},{"date":"2026-03-08","gross_revenue":39149.0,"discount_amount":4469.0,"net_revenue":34680.0,"orders":140,"diners":392,"spend_per_guest":88.469388,"spend_per_order":247.714286,"seating_rate":2.2529,"table_open_rate":3.5,"table_turnover_rate":2.5,"tables":140},{"date":"2026-03-09","gross_revenue":8180.0,"discount_amount":990.7,"net_revenue":7189.3,"orders":33,"diners":78,"spend_per_guest":92.170513,"spend_per_order":217.857576,"seating_rate":0.4483,"table_open_rate":0.825,"table_turnover_rate":0.0,"tables":33},{"date":"2026-03-10","gross_revenue":11804.0,"discount_amount":1116.7,"net_revenue":10687.3,"orders":35,"diners":118,"spend_per_guest":90.570339,"spend_per_order":305.351429,"seating_rate":0.6782,"table_open_rate":0.875,"table_turnover_rate":0.0,"tables":35},{"date":"2026-03-11","gross_revenue":9803.0,"discount_amount":746.9,"net_revenue":9056.1,"orders":31,"diners":101,"spend_per_guest":89.664356,"spend_per_order":292.132258,"seating_rate":0.5805,"table_open_rate":0.775,"table_turnover_rate":0.0,"tables":31},{"date":"2026-03-12","gross_revenue":9973.0,"discount_amount":632.7,"net_revenue":9340.3,"orders":41,"diners":98,"spend_per_guest":95.309184,"spend_per_order":227.812195,"seating_rate":0.5632,"table_open_rate":1.025,"table_turnover_rate":0.025,"tables":41},{"date":"2026-03-13","gross_revenue":17507.0,"discount_amount":2271.4,"net_revenue":15235.6,"orders":60,"diners":182,"spend_per_guest":83.712088,"spend_per_order":253.926667,"seating_rate":1.046,"table_open_rate":1.5,"table_turnover_rate":0.5,"tables":60},{"date":"2026-03-14","gross_revenue":21260.4,"discount_amount":2386.4,"net_revenue":18874.0,"orders":79,"diners":239,"spend_per_guest":78.970711,"spend_per_order":238.911392,"seating_rate":1.3736,"table_open_rate":1.95,"table_turnover_rate":0.95,"tables":78},{"date":"2026-03-15","gross_revenue":28790.4,"discount_amount":3159.7,"net_revenue":25630.7,"orders":91,"diners":275,"spend_per_guest":93.202545,"spend_per_order":281.656044,"seating_rate":1.5805,"table_open_rate":2.275,"table_turnover_rate":1.275,"tables":91},{"date":"2026-03-16","gross_revenue":13309.7,"discount_amount":1510.9,"net_revenue":11798.8,"orders":49,"diners":134,"spend_per_guest":88.050746,"spend_per_order":240.791837,"seating_rate":0.7701,"table_open_rate":1.225,"table_turnover_rate":0.225,"tables":49},{"date":"2026-03-17","gross_revenue":7915.9,"discount_amount":503.1,"net_revenue":7412.8,"orders":31,"diners":84,"spend_per_guest":88.247619,"spend_per_order":239.122581,"seating_rate":0.4828,"table_open_rate":0.775,"table_turnover_rate":0.0,"tables":31},{"date":"2026-03-18","gross_revenue":8834.7,"discount_amount":800.2,"net_revenue":8034.5,"orders":32,"diners":87,"spend_per_guest":92.350575,"spend_per_order":251.078125,"seating_rate":0.5,"table_open_rate":0.8,"table_turnover_rate":0.0,"tables":32},{"date":"2026-03-19","gross_revenue":8667.0,"discount_amount":682.0,"net_revenue":7985.0,"orders":30,"diners":81,"spend_per_guest":98.580247,"spend_per_order":266.166667,"seating_rate":0.4655,"table_open_rate":0.75,"table_turnover_rate":0.0,"tables":30},{"date":"2026-03-20","gross_revenue":15790.9,"discount_amount":1844.5,"net_revenue":13946.4,"orders":58,"diners":159,"spend_per_guest":87.713208,"spend_per_order":240.455172,"seating_rate":0.9138,"table_open_rate":1.45,"table_turnover_rate":0.45,"tables":58},{"date":"2026-03-21","gross_revenue":23094.5,"discount_amount":2381.4,"net_revenue":20713.1,"orders":85,"diners":247,"spend_per_guest":83.858704,"spend_per_order":243.683529,"seating_rate":1.4195,"table_open_rate":2.125,"table_turnover_rate":1.125,"tables":85},{"date":"2026-03-22","gross_revenue":26506.5,"discount_amount":3725.4,"net_revenue":22781.1,"orders":91,"diners":254,"spend_per_guest":89.68937,"spend_per_order":250.341758,"seating_rate":1.4598,"table_open_rate":2.275,"table_turnover_rate":1.275,"tables":91},{"date":"2026-03-23","gross_revenue":14251.6,"discount_amount":1929.7,"net_revenue":12321.9,"orders":43,"diners":152,"spend_per_guest":81.065132,"spend_per_order":286.555814,"seating_rate":0.8736,"table_open_rate":1.075,"table_turnover_rate":0.075,"tables":43},{"date":"2026-03-24","gross_revenue":10164.7,"discount_amount":1022.3,"net_revenue":9142.4,"orders":33,"diners":97,"spend_per_guest":94.251546,"spend_per_order":277.042424,"seating_rate":0.5575,"table_open_rate":0.825,"table_turnover_rate":0.0,"tables":33},{"date":"2026-03-25","gross_revenue":5595.7,"discount_amount":772.2,"net_revenue":4823.5,"orders":23,"diners":56,"spend_per_guest":86.133929,"spend_per_order":209.717391,"seating_rate":0.3218,"table_open_rate":0.575,"table_turnover_rate":0.0,"tables":23},{"date":"2026-03-26","gross_revenue":10515.7,"discount_amount":857.6,"net_revenue":9658.1,"orders":33,"diners":100,"spend_per_guest":96.581,"spend_per_order":292.669697,"seating_rate":0.5747,"table_open_rate":0.825,"table_turnover_rate":0.0,"tables":33},{"date":"2026-03-27","gross_revenue":15351.0,"discount_amount":3776.3,"net_revenue":11574.7,"orders":56,"diners":154,"spend_per_guest":75.16039,"spend_per_order":206.691071,"seating_rate":0.8851,"table_open_rate":1.4,"table_turnover_rate":0.4,"tables":56},{"date":"2026-03-28","gross_revenue":27692.1,"discount_amount":4094.7,"net_revenue":23597.4,"orders":95,"diners":281,"spend_per_guest":83.976512,"spend_per_order":248.393684,"seating_rate":1.6149,"table_open_rate":2.375,"table_turnover_rate":1.375,"tables":95},{"date":"2026-03-29","gross_revenue":20883.5,"discount_amount":2429.0,"net_revenue":18454.5,"orders":74,"diners":235,"spend_per_guest":78.529787,"spend_per_order":249.385135,"seating_rate":1.3506,"table_open_rate":1.85,"table_turnover_rate":0.85,"tables":74},{"date":"2026-03-30","gross_revenue":9713.9,"discount_amount":1898.0,"net_revenue":7815.9,"orders":38,"diners":95,"spend_per_guest":82.272632,"spend_per_order":205.681579,"seating_rate":0.546,"table_open_rate":0.95,"table_turnover_rate":0.0,"tables":38},{"date":"2026-03-31","gross_revenue":9896.5,"discount_amount":1543.1,"net_revenue":8353.4,"orders":36,"diners":91,"spend_per_guest":91.795604,"spend_per_order":232.038889,"seating_rate":0.523,"table_open_rate":0.9,"table_turnover_rate":0.0,"tables":36},{"date":"2026-04-01","gross_revenue":11542.7,"discount_amount":1191.0,"net_revenue":10351.7,"orders":46,"diners":118,"spend_per_guest":87.726271,"spend_per_order":225.036957,"seating_rate":0.6782,"table_open_rate":1.15,"table_turnover_rate":0.15,"tables":46},{"date":"2026-04-02","gross_revenue":12080.0,"discount_amount":1106.2,"net_revenue":10973.8,"orders":49,"diners":131,"spend_per_guest":83.769466,"spend_per_order":223.955102,"seating_rate":0.7529,"table_open_rate":1.225,"table_turnover_rate":0.225,"tables":49},{"date":"2026-04-03","gross_revenue":20434.6,"discount_amount":2661.2,"net_revenue":17773.4,"orders":83,"diners":215,"spend_per_guest":82.666977,"spend_per_order":214.137349,"seating_rate":1.2356,"table_open_rate":2.075,"table_turnover_rate":1.075,"tables":83},{"date":"2026-04-04","gross_revenue":24658.6,"discount_amount":3648.1,"net_revenue":21010.5,"orders":91,"diners":287,"spend_per_guest":73.207317,"spend_per_order":230.884615,"seating_rate":1.6494,"table_open_rate":2.275,"table_turnover_rate":1.275,"tables":91},{"date":"2026-04-05","gross_revenue":25577.0,"discount_amount":3606.2,"net_revenue":21970.8,"orders":92,"diners":297,"spend_per_guest":73.975758,"spend_per_order":238.813043,"seating_rate":1.7069,"table_open_rate":2.3,"table_turnover_rate":1.3,"tables":92},{"date":"2026-04-06","gross_revenue":23675.1,"discount_amount":3667.1,"net_revenue":20008.0,"orders":85,"diners":246,"spend_per_guest":81.333333,"spend_per_order":235.388235,"seating_rate":1.4138,"table_open_rate":2.125,"table_turnover_rate":1.125,"tables":85},{"date":"2026-04-07","gross_revenue":10292.0,"discount_amount":1669.7,"net_revenue":8622.3,"orders":43,"diners":103,"spend_per_guest":83.71165,"spend_per_order":200.518605,"seating_rate":0.592,"table_open_rate":1.075,"table_turnover_rate":0.075,"tables":43},{"date":"2026-04-08","gross_revenue":8651.0,"discount_amount":1407.4,"net_revenue":7243.6,"orders":35,"diners":84,"spend_per_guest":86.233333,"spend_per_order":206.96,"seating_rate":0.4828,"table_open_rate":0.875,"table_turnover_rate":0.0,"tables":35},{"date":"2026-04-09","gross_revenue":9607.0,"discount_amount":1090.0,"net_revenue":8517.0,"orders":34,"diners":94,"spend_per_guest":90.606383,"spend_per_order":250.5,"seating_rate":0.5402,"table_open_rate":0.85,"table_turnover_rate":0.0,"tables":34},{"date":"2026-04-10","gross_revenue":15478.1,"discount_amount":3035.8,"net_revenue":12442.3,"orders":63,"diners":164,"spend_per_guest":75.867683,"spend_per_order":197.496825,"seating_rate":0.9425,"table_open_rate":1.575,"table_turnover_rate":0.575,"tables":63},{"date":"2026-04-11","gross_revenue":28634.4,"discount_amount":5492.5,"net_revenue":23141.9,"orders":109,"diners":304,"spend_per_guest":76.124671,"spend_per_order":212.311009,"seating_rate":1.7471,"table_open_rate":2.725,"table_turnover_rate":1.725,"tables":109},{"date":"2026-04-12","gross_revenue":16351.1,"discount_amount":3050.0,"net_revenue":13301.1,"orders":65,"diners":167,"spend_per_guest":79.647305,"spend_per_order":204.632308,"seating_rate":0.9598,"table_open_rate":1.625,"table_turnover_rate":0.625,"tables":65},{"date":"2026-04-13","gross_revenue":8716.0,"discount_amount":1643.7,"net_revenue":7072.3,"orders":35,"diners":77,"spend_per_guest":91.848052,"spend_per_order":202.065714,"seating_rate":0.4425,"table_open_rate":0.875,"table_turnover_rate":0.0,"tables":35},{"date":"2026-04-14","gross_revenue":10316.0,"discount_amount":1668.1,"net_revenue":8647.9,"orders":39,"diners":110,"spend_per_guest":78.617273,"spend_per_order":221.741026,"seating_rate":0.6322,"table_open_rate":0.975,"table_turnover_rate":0.0,"tables":39},{"date":"2026-04-15","gross_revenue":10300.0,"discount_amount":1639.6,"net_revenue":8660.4,"orders":39,"diners":107,"spend_per_guest":80.938318,"spend_per_order":222.061538,"seating_rate":0.6149,"table_open_rate":0.975,"table_turnover_rate":0.0,"tables":39},{"date":"2026-04-16","gross_revenue":8815.0,"discount_amount":1603.7,"net_revenue":7211.3,"orders":35,"diners":89,"spend_per_guest":81.025843,"spend_per_order":206.037143,"seating_rate":0.5115,"table_open_rate":0.875,"table_turnover_rate":0.0,"tables":35},{"date":"2026-04-17","gross_revenue":15679.0,"discount_amount":2837.8,"net_revenue":12841.2,"orders":58,"diners":151,"spend_per_guest":85.04106,"spend_per_order":221.4,"seating_rate":0.8678,"table_open_rate":1.45,"table_turnover_rate":0.45,"tables":58},{"date":"2026-04-18","gross_revenue":21227.5,"discount_amount":3526.1,"net_revenue":17701.4,"orders":79,"diners":229,"spend_per_guest":77.29869,"spend_per_order":224.068354,"seating_rate":1.3161,"table_open_rate":1.975,"table_turnover_rate":0.975,"tables":79},{"date":"2026-04-19","gross_revenue":21624.8,"discount_amount":3419.8,"net_revenue":18205.0,"orders":82,"diners":223,"spend_per_guest":81.636771,"spend_per_order":222.012195,"seating_rate":1.2816,"table_open_rate":2.05,"table_turnover_rate":1.05,"tables":82},{"date":"2026-04-20","gross_revenue":9843.0,"discount_amount":1257.3,"net_revenue":8585.7,"orders":38,"diners":91,"spend_per_guest":94.348352,"spend_per_order":225.939474,"seating_rate":0.523,"table_open_rate":0.95,"table_turnover_rate":0.0,"tables":38},{"date":"2026-04-21","gross_revenue":10061.0,"discount_amount":1406.5,"net_revenue":8654.5,"orders":39,"diners":96,"spend_per_guest":90.151042,"spend_per_order":221.910256,"seating_rate":0.5517,"table_open_rate":0.975,"table_turnover_rate":0.0,"tables":39},{"date":"2026-04-22","gross_revenue":11097.0,"discount_amount":1666.9,"net_revenue":9430.1,"orders":43,"diners":106,"spend_per_guest":88.963208,"spend_per_order":219.304651,"seating_rate":0.6092,"table_open_rate":1.075,"table_turnover_rate":0.075,"tables":43},{"date":"2026-04-23","gross_revenue":7468.0,"discount_amount":767.6,"net_revenue":6700.4,"orders":31,"diners":82,"spend_per_guest":81.712195,"spend_per_order":216.141935,"seating_rate":0.4713,"table_open_rate":0.775,"table_turnover_rate":0.0,"tables":31},{"date":"2026-04-24","gross_revenue":13187.6,"discount_amount":2224.2,"net_revenue":10963.4,"orders":53,"diners":153,"spend_per_guest":71.656209,"spend_per_order":206.856604,"seating_rate":0.8793,"table_open_rate":1.325,"table_turnover_rate":0.325,"tables":53},{"date":"2026-04-25","gross_revenue":15895.8,"discount_amount":2654.1,"net_revenue":13241.7,"orders":60,"diners":171,"spend_per_guest":77.436842,"spend_per_order":220.695,"seating_rate":0.9828,"table_open_rate":1.5,"table_turnover_rate":0.5,"tables":60},{"date":"2026-04-26","gross_revenue":14657.7,"discount_amount":2560.5,"net_revenue":12097.2,"orders":55,"diners":164,"spend_per_guest":73.763415,"spend_per_order":219.949091,"seating_rate":0.9425,"table_open_rate":1.375,"table_turnover_rate":0.375,"tables":55},{"date":"2026-04-27","gross_revenue":6553.0,"discount_amount":1110.7,"net_revenue":5442.3,"orders":28,"diners":76,"spend_per_guest":71.609211,"spend_per_order":194.367857,"seating_rate":0.4368,"table_open_rate":0.7,"table_turnover_rate":0.0,"tables":28},{"date":"2026-04-28","gross_revenue":12026.0,"discount_amount":1588.0,"net_revenue":10438.0,"orders":40,"diners":121,"spend_per_guest":86.264463,"spend_per_order":260.95,"seating_rate":0.6954,"table_open_rate":1.0,"table_turnover_rate":0.0,"tables":40},{"date":"2026-04-29","gross_revenue":11380.0,"discount_amount":2689.7,"net_revenue":8690.3,"orders":36,"diners":103,"spend_per_guest":84.371845,"spend_per_order":241.397222,"seating_rate":0.592,"table_open_rate":0.9,"table_turnover_rate":0.0,"tables":36},{"date":"2026-04-30","gross_revenue":20199.5,"discount_amount":2166.9,"net_revenue":18032.6,"orders":61,"diners":214,"spend_per_guest":84.264486,"spend_per_order":295.616393,"seating_rate":1.2299,"table_open_rate":1.525,"table_turnover_rate":0.525,"tables":61},{"date":"2026-05-01","gross_revenue":13483.1,"discount_amount":1273.0,"net_revenue":12210.1,"orders":53,"diners":147,"spend_per_guest":83.061905,"spend_per_order":230.379245,"seating_rate":0.8448,"table_open_rate":1.325,"table_turnover_rate":0.325,"tables":53},{"date":"2026-05-02","gross_revenue":24024.5,"discount_amount":1723.9,"net_revenue":22300.6,"orders":85,"diners":268,"spend_per_guest":83.211194,"spend_per_order":262.36,"seating_rate":1.5402,"table_open_rate":2.125,"table_turnover_rate":1.125,"tables":85},{"date":"2026-05-03","gross_revenue":15533.1,"discount_amount":1453.8,"net_revenue":14079.3,"orders":58,"diners":184,"spend_per_guest":76.517935,"spend_per_order":242.746552,"seating_rate":1.0575,"table_open_rate":1.45,"table_turnover_rate":0.45,"tables":58},{"date":"2026-05-04","gross_revenue":18956.8,"discount_amount":2231.3,"net_revenue":16725.5,"orders":71,"diners":203,"spend_per_guest":82.391626,"spend_per_order":235.570423,"seating_rate":1.1667,"table_open_rate":1.775,"table_turnover_rate":0.775,"tables":71},{"date":"2026-05-05","gross_revenue":22068.0,"discount_amount":3350.0,"net_revenue":18718.0,"orders":82,"diners":211,"spend_per_guest":88.7109,"spend_per_order":228.268293,"seating_rate":1.2126,"table_open_rate":2.05,"table_turnover_rate":1.05,"tables":82},{"date":"2026-05-06","gross_revenue":5757.9,"discount_amount":730.9,"net_revenue":5027.0,"orders":25,"diners":64,"spend_per_guest":78.546875,"spend_per_order":201.08,"seating_rate":0.3678,"table_open_rate":0.625,"table_turnover_rate":0.0,"tables":25},{"date":"2026-05-07","gross_revenue":7299.9,"discount_amount":1171.6,"net_revenue":6128.3,"orders":25,"diners":65,"spend_per_guest":94.281538,"spend_per_order":245.132,"seating_rate":0.3736,"table_open_rate":0.625,"table_turnover_rate":0.0,"tables":25},{"date":"2026-05-08","gross_revenue":11887.8,"discount_amount":2892.2,"net_revenue":8995.6,"orders":36,"diners":121,"spend_per_guest":74.343802,"spend_per_order":249.877778,"seating_rate":0.6954,"table_open_rate":0.9,"table_turnover_rate":0.0,"tables":36},{"date":"2026-05-09","gross_revenue":14136.9,"discount_amount":3376.8,"net_revenue":10760.1,"orders":47,"diners":144,"spend_per_guest":74.722917,"spend_per_order":228.938298,"seating_rate":0.8276,"table_open_rate":1.175,"table_turnover_rate":0.175,"tables":47},{"date":"2026-05-10","gross_revenue":30647.4,"discount_amount":5394.1,"net_revenue":25253.3,"orders":106,"diners":306,"spend_per_guest":82.527124,"spend_per_order":238.238679,"seating_rate":1.7586,"table_open_rate":2.65,"table_turnover_rate":1.65,"tables":106},{"date":"2026-05-11","gross_revenue":5748.5,"discount_amount":1227.9,"net_revenue":4520.6,"orders":21,"diners":55,"spend_per_guest":82.192727,"spend_per_order":215.266667,"seating_rate":0.3161,"table_open_rate":0.525,"table_turnover_rate":0.0,"tables":21},{"date":"2026-05-12","gross_revenue":7217.7,"discount_amount":1001.1,"net_revenue":6216.6,"orders":32,"diners":75,"spend_per_guest":82.888,"spend_per_order":194.26875,"seating_rate":0.431,"table_open_rate":0.8,"table_turnover_rate":0.0,"tables":32},{"date":"2026-05-13","gross_revenue":11344.7,"discount_amount":1293.4,"net_revenue":10051.3,"orders":41,"diners":117,"spend_per_guest":85.908547,"spend_per_order":245.153659,"seating_rate":0.6724,"table_open_rate":1.025,"table_turnover_rate":0.025,"tables":41},{"date":"2026-05-14","gross_revenue":8267.0,"discount_amount":1130.8,"net_revenue":7136.2,"orders":34,"diners":75,"spend_per_guest":95.149333,"spend_per_order":209.888235,"seating_rate":0.431,"table_open_rate":0.85,"table_turnover_rate":0.0,"tables":34},{"date":"2026-05-15","gross_revenue":11753.6,"discount_amount":1549.6,"net_revenue":10204.0,"orders":43,"diners":119,"spend_per_guest":85.747899,"spend_per_order":237.302326,"seating_rate":0.6839,"table_open_rate":1.075,"table_turnover_rate":0.075,"tables":43},{"date":"2026-05-16","gross_revenue":21260.5,"discount_amount":3402.9,"net_revenue":17857.6,"orders":77,"diners":229,"spend_per_guest":77.980786,"spend_per_order":231.916883,"seating_rate":1.3161,"table_open_rate":1.925,"table_turnover_rate":0.925,"tables":77},{"date":"2026-05-17","gross_revenue":18053.5,"discount_amount":3162.7,"net_revenue":14890.8,"orders":65,"diners":180,"spend_per_guest":82.726667,"spend_per_order":229.089231,"seating_rate":1.0345,"table_open_rate":1.625,"table_turnover_rate":0.625,"tables":65},{"date":"2026-05-18","gross_revenue":7757.9,"discount_amount":1001.9,"net_revenue":6756.0,"orders":29,"diners":77,"spend_per_guest":87.74026,"spend_per_order":232.965517,"seating_rate":0.4425,"table_open_rate":0.725,"table_turnover_rate":0.0,"tables":29},{"date":"2026-05-19","gross_revenue":10503.6,"discount_amount":1152.0,"net_revenue":9351.6,"orders":37,"diners":101,"spend_per_guest":92.590099,"spend_per_order":252.745946,"seating_rate":0.5805,"table_open_rate":0.925,"table_turnover_rate":0.0,"tables":37},{"date":"2026-05-20","gross_revenue":33146.0,"discount_amount":6991.9,"net_revenue":26154.1,"orders":117,"diners":292,"spend_per_guest":89.568836,"spend_per_order":223.539316,"seating_rate":1.6782,"table_open_rate":2.925,"table_turnover_rate":1.925,"tables":117},{"date":"2026-05-21","gross_revenue":9065.9,"discount_amount":1462.3,"net_revenue":7603.6,"orders":34,"diners":87,"spend_per_guest":87.397701,"spend_per_order":223.635294,"seating_rate":0.5,"table_open_rate":0.85,"table_turnover_rate":0.0,"tables":34},{"date":"2026-05-22","gross_revenue":13680.6,"discount_amount":2725.7,"net_revenue":10954.9,"orders":54,"diners":141,"spend_per_guest":77.694326,"spend_per_order":202.868519,"seating_rate":0.8103,"table_open_rate":1.35,"table_turnover_rate":0.35,"tables":54},{"date":"2026-05-23","gross_revenue":19235.2,"discount_amount":2763.06,"net_revenue":16472.14,"orders":72,"diners":206,"spend_per_guest":79.961845,"spend_per_order":228.779722,"seating_rate":1.1839,"table_open_rate":1.8,"table_turnover_rate":0.8,"tables":72},{"date":"2026-05-24","gross_revenue":21527.7,"discount_amount":3669.4,"net_revenue":17858.3,"orders":75,"diners":235,"spend_per_guest":75.992766,"spend_per_order":238.110667,"seating_rate":1.3506,"table_open_rate":1.875,"table_turnover_rate":0.875,"tables":75},{"date":"2026-05-25","gross_revenue":6322.0,"discount_amount":990.6,"net_revenue":5331.4,"orders":25,"diners":68,"spend_per_guest":78.402941,"spend_per_order":213.256,"seating_rate":0.3908,"table_open_rate":0.625,"table_turnover_rate":0.0,"tables":25},{"date":"2026-05-26","gross_revenue":9192.8,"discount_amount":1259.0,"net_revenue":7933.8,"orders":32,"diners":99,"spend_per_guest":80.139394,"spend_per_order":247.93125,"seating_rate":0.569,"table_open_rate":0.8,"table_turnover_rate":0.0,"tables":32},{"date":"2026-05-27","gross_revenue":6367.8,"discount_amount":836.7,"net_revenue":5531.1,"orders":27,"diners":65,"spend_per_guest":85.093846,"spend_per_order":204.855556,"seating_rate":0.3736,"table_open_rate":0.675,"table_turnover_rate":0.0,"tables":27},{"date":"2026-05-28","gross_revenue":6106.0,"discount_amount":1359.6,"net_revenue":4746.4,"orders":24,"diners":64,"spend_per_guest":74.1625,"spend_per_order":197.766667,"seating_rate":0.3678,"table_open_rate":0.6,"table_turnover_rate":0.0,"tables":24},{"date":"2026-05-29","gross_revenue":17948.6,"discount_amount":3273.2,"net_revenue":14675.4,"orders":63,"diners":186,"spend_per_guest":78.9,"spend_per_order":232.942857,"seating_rate":1.069,"table_open_rate":1.575,"table_turnover_rate":0.575,"tables":63},{"date":"2026-05-30","gross_revenue":23313.7,"discount_amount":3482.7,"net_revenue":19831.0,"orders":88,"diners":253,"spend_per_guest":78.383399,"spend_per_order":225.352273,"seating_rate":1.454,"table_open_rate":2.2,"table_turnover_rate":1.2,"tables":88},{"date":"2026-05-31","gross_revenue":22991.7,"discount_amount":3799.1,"net_revenue":19192.6,"orders":83,"diners":248,"spend_per_guest":77.389516,"spend_per_order":231.236145,"seating_rate":1.4253,"table_open_rate":2.075,"table_turnover_rate":1.075,"tables":83},{"date":"2026-06-01","gross_revenue":28724.8,"discount_amount":3686.7,"net_revenue":25038.1,"orders":113,"diners":366,"spend_per_guest":68.410109,"spend_per_order":221.576106,"seating_rate":2.1034,"table_open_rate":2.825,"table_turnover_rate":1.825,"tables":113},{"date":"2026-06-02","gross_revenue":8649.8,"discount_amount":1109.3,"net_revenue":7540.5,"orders":36,"diners":83,"spend_per_guest":90.849398,"spend_per_order":209.458333,"seating_rate":0.477,"table_open_rate":0.9,"table_turnover_rate":0.0,"tables":36},{"date":"2026-06-03","gross_revenue":8525.0,"discount_amount":1348.7,"net_revenue":7176.3,"orders":31,"diners":88,"spend_per_guest":81.548864,"spend_per_order":231.493548,"seating_rate":0.5057,"table_open_rate":0.775,"table_turnover_rate":0.0,"tables":31},{"date":"2026-06-04","gross_revenue":7940.7,"discount_amount":789.4,"net_revenue":7151.3,"orders":31,"diners":91,"spend_per_guest":78.585714,"spend_per_order":230.687097,"seating_rate":0.523,"table_open_rate":0.775,"table_turnover_rate":0.0,"tables":31},{"date":"2026-06-05","gross_revenue":12511.0,"discount_amount":2606.4,"net_revenue":9904.6,"orders":45,"diners":126,"spend_per_guest":78.607937,"spend_per_order":220.102222,"seating_rate":0.7241,"table_open_rate":1.125,"table_turnover_rate":0.125,"tables":45},{"date":"2026-06-06","gross_revenue":21603.6,"discount_amount":3488.0,"net_revenue":18115.6,"orders":77,"diners":240,"spend_per_guest":75.481667,"spend_per_order":235.267532,"seating_rate":1.3793,"table_open_rate":1.925,"table_turnover_rate":0.925,"tables":77},{"date":"2026-06-07","gross_revenue":17753.6,"discount_amount":3623.1,"net_revenue":14130.5,"orders":63,"diners":197,"spend_per_guest":71.728426,"spend_per_order":224.293651,"seating_rate":1.1322,"table_open_rate":1.575,"table_turnover_rate":0.575,"tables":63},{"date":"2026-06-08","gross_revenue":9541.8,"discount_amount":1436.2,"net_revenue":8105.6,"orders":34,"diners":94,"spend_per_guest":86.229787,"spend_per_order":238.4,"seating_rate":0.5402,"table_open_rate":0.85,"table_turnover_rate":0.0,"tables":34},{"date":"2026-06-09","gross_revenue":14705.9,"discount_amount":1971.7,"net_revenue":12734.2,"orders":54,"diners":181,"spend_per_guest":70.354696,"spend_per_order":235.818519,"seating_rate":1.0402,"table_open_rate":1.35,"table_turnover_rate":0.35,"tables":54},{"date":"2026-06-10","gross_revenue":8371.8,"discount_amount":1897.8,"net_revenue":6474.0,"orders":29,"diners":78,"spend_per_guest":83.0,"spend_per_order":223.241379,"seating_rate":0.4483,"table_open_rate":0.725,"table_turnover_rate":0.0,"tables":29},{"date":"2026-06-11","gross_revenue":9144.8,"discount_amount":1660.4,"net_revenue":7484.4,"orders":37,"diners":91,"spend_per_guest":82.246154,"spend_per_order":202.281081,"seating_rate":0.523,"table_open_rate":0.925,"table_turnover_rate":0.0,"tables":37},{"date":"2026-06-12","gross_revenue":12312.6,"discount_amount":2276.9,"net_revenue":10035.7,"orders":46,"diners":127,"spend_per_guest":79.02126,"spend_per_order":218.167391,"seating_rate":0.7299,"table_open_rate":1.15,"table_turnover_rate":0.15,"tables":46},{"date":"2026-06-13","gross_revenue":23891.9,"discount_amount":4273.3,"net_revenue":19618.6,"orders":87,"diners":254,"spend_per_guest":77.238583,"spend_per_order":225.501149,"seating_rate":1.4598,"table_open_rate":2.175,"table_turnover_rate":1.175,"tables":87},{"date":"2026-06-14","gross_revenue":25618.8,"discount_amount":4172.4,"net_revenue":21446.4,"orders":88,"diners":268,"spend_per_guest":80.023881,"spend_per_order":243.709091,"seating_rate":1.5402,"table_open_rate":2.2,"table_turnover_rate":1.2,"tables":88},{"date":"2026-06-15","gross_revenue":10775.8,"discount_amount":1741.3,"net_revenue":9034.5,"orders":39,"diners":108,"spend_per_guest":83.652778,"spend_per_order":231.653846,"seating_rate":0.6207,"table_open_rate":0.975,"table_turnover_rate":0.0,"tables":39},{"date":"2026-06-16","gross_revenue":12568.9,"discount_amount":1836.1,"net_revenue":10732.8,"orders":45,"diners":131,"spend_per_guest":81.929771,"spend_per_order":238.506667,"seating_rate":0.7529,"table_open_rate":1.125,"table_turnover_rate":0.125,"tables":45},{"date":"2026-06-17","gross_revenue":13200.0,"discount_amount":3165.9,"net_revenue":10034.1,"orders":48,"diners":138,"spend_per_guest":72.71087,"spend_per_order":209.04375,"seating_rate":0.7931,"table_open_rate":1.2,"table_turnover_rate":0.2,"tables":48},{"date":"2026-06-18","gross_revenue":16674.7,"discount_amount":3048.9,"net_revenue":13625.8,"orders":64,"diners":170,"spend_per_guest":80.151765,"spend_per_order":212.903125,"seating_rate":0.977,"table_open_rate":1.6,"table_turnover_rate":0.6,"tables":64},{"date":"2026-06-19","gross_revenue":23709.0,"discount_amount":2063.8,"net_revenue":21645.2,"orders":95,"diners":267,"spend_per_guest":81.068165,"spend_per_order":227.844211,"seating_rate":1.5345,"table_open_rate":2.375,"table_turnover_rate":1.375,"tables":95},{"date":"2026-06-20","gross_revenue":27449.3,"discount_amount":3520.8,"net_revenue":23928.5,"orders":96,"diners":319,"spend_per_guest":75.010972,"spend_per_order":249.255208,"seating_rate":1.8333,"table_open_rate":2.4,"table_turnover_rate":1.4,"tables":96},{"date":"2026-06-21","gross_revenue":21735.0,"discount_amount":3286.5,"net_revenue":18448.5,"orders":85,"diners":243,"spend_per_guest":75.919753,"spend_per_order":217.041176,"seating_rate":1.3966,"table_open_rate":2.125,"table_turnover_rate":1.125,"tables":85},{"date":"2026-06-22","gross_revenue":11178.0,"discount_amount":1537.9,"net_revenue":9640.1,"orders":40,"diners":109,"spend_per_guest":88.441284,"spend_per_order":241.0025,"seating_rate":0.6264,"table_open_rate":1.0,"table_turnover_rate":0.0,"tables":40},{"date":"2026-06-23","gross_revenue":9262.0,"discount_amount":1255.1,"net_revenue":8006.9,"orders":36,"diners":97,"spend_per_guest":82.545361,"spend_per_order":222.413889,"seating_rate":0.5575,"table_open_rate":0.9,"table_turnover_rate":0.0,"tables":36},{"date":"2026-06-24","gross_revenue":10921.0,"discount_amount":1888.4,"net_revenue":9032.6,"orders":42,"diners":119,"spend_per_guest":75.904202,"spend_per_order":215.061905,"seating_rate":0.6839,"table_open_rate":1.05,"table_turnover_rate":0.05,"tables":42},{"date":"2026-06-25","gross_revenue":10739.0,"discount_amount":2290.4,"net_revenue":8448.6,"orders":39,"diners":105,"spend_per_guest":80.462857,"spend_per_order":216.630769,"seating_rate":0.6034,"table_open_rate":0.975,"table_turnover_rate":0.0,"tables":39},{"date":"2026-06-26","gross_revenue":18451.0,"discount_amount":3579.9,"net_revenue":14871.1,"orders":68,"diners":191,"spend_per_guest":77.859162,"spend_per_order":218.692647,"seating_rate":1.0977,"table_open_rate":1.7,"table_turnover_rate":0.7,"tables":68},{"date":"2026-06-27","gross_revenue":23548.0,"discount_amount":3265.7,"net_revenue":20282.3,"orders":83,"diners":269,"spend_per_guest":75.398885,"spend_per_order":244.36506,"seating_rate":1.546,"table_open_rate":2.075,"table_turnover_rate":1.075,"tables":83},{"date":"2026-06-28","gross_revenue":18571.0,"discount_amount":3915.3,"net_revenue":14655.7,"orders":70,"diners":195,"spend_per_guest":75.157436,"spend_per_order":209.367143,"seating_rate":1.1207,"table_open_rate":1.75,"table_turnover_rate":0.75,"tables":70},{"date":"2026-06-29","gross_revenue":11559.0,"discount_amount":1911.4,"net_revenue":9647.6,"orders":39,"diners":114,"spend_per_guest":84.62807,"spend_per_order":247.374359,"seating_rate":0.6552,"table_open_rate":0.975,"table_turnover_rate":0.0,"tables":39},{"date":"2026-06-30","gross_revenue":13697.0,"discount_amount":1358.6,"net_revenue":12338.4,"orders":49,"diners":138,"spend_per_guest":89.408696,"spend_per_order":251.804082,"seating_rate":0.7931,"table_open_rate":1.225,"table_turnover_rate":0.225,"tables":49}]